LICENSE
MANIFEST.in
README.md
setup.py
django_smsish.egg-info/PKG-INFO
django_smsish.egg-info/SOURCES.txt
django_smsish.egg-info/dependency_links.txt
django_smsish.egg-info/top_level.txt
example/__init__.py
example/settings.py
example/urls.py
example/wsgi.py
smsish/__init__.py
smsish/admin.py
smsish/models.py
smsish/tasks.py
smsish/tests.py
smsish/views.py
smsish/mail/__init__.py
smsish/mail/utils.py
smsish/mail/backends/__init__.py
smsish/mail/backends/mailtrap.py
smsish/migrations/__init__.py
smsish/sms/__init__.py
smsish/sms/message.py
smsish/sms/backends/__init__.py
smsish/sms/backends/base.py
smsish/sms/backends/console.py
smsish/sms/backends/dummy.py
smsish/sms/backends/filebased.py
smsish/sms/backends/locmem.py
smsish/sms/backends/mailcatcher.py
smsish/sms/backends/mailtrap.py
smsish/sms/backends/rq.py
smsish/sms/backends/smtp.py
smsish/sms/backends/twilio.py