Metadata-Version: 1.1
Name: django-smsish
Version: 1.3.2
Summary: A simple Django app to send SMS messages using an API similar to that of django.core.mail.
Home-page: https://github.com/RyanBalfanz/django-smsish
Author: Ryan Balfanz
Author-email: ryan@ryanbalfanz.net
License: MIT
Platform: UNKNOWN
Classifier: Development Status :: 4 - Beta
Classifier: Environment :: Web Environment
Classifier: Framework :: Django
Classifier: Framework :: Django :: 1.8
Classifier: Framework :: Django :: 1.9
Classifier: Intended Audience :: Developers
Classifier: License :: OSI Approved :: MIT License
Classifier: Operating System :: OS Independent
Classifier: Programming Language :: Python
Classifier: Programming Language :: Python :: 3
Classifier: Programming Language :: Python :: 3.4
Classifier: Programming Language :: Python :: 3.5
Classifier: Topic :: Communications
Classifier: Topic :: Communications :: Telephony
